{"solution":["#<Structs::Item:0x5d22850e>","#<Structs::Item:0x779a70a5>","#<Structs::Item:0x75329463>","#<Structs::Item:0xf513b6f>","#<Structs::Item:0x4612d57e>","#<Structs::Item:0x62298a41>","#<Structs::Item:0x3598beb>","#<Structs::Item:0x5d542ac>","#<Structs::Item:0x553cde4d>","#<Structs::Item:0x7be92d29>","#<Structs::Item:0x3420e76c>","#<Structs::Item:0x1b4f0366>","#<Structs::Item:0x283268f4>","#<Structs::Item:0x1a0088be>","#<Structs::Item:0x29280715>","#<Structs::Item:0x4a9f7565>","#<Structs::Item:0x7151c10a>","#<Structs::Item:0x6f8ae2e6>","#<Structs::Item:0x67350ad>","#<Structs::Item:0x37f6295b>","#<Structs::Item:0x48d0e73e>","#<Structs::Item:0x7075a110>","#<Structs::Item:0x6c9f618b>","#<Structs::Item:0x6aa521b2>","#<Structs::Item:0x2583c2cf>","#<Structs::Item:0x78239a4e>","#<Structs::Item:0x6f272ff8>","#<Structs::Item:0x2c4c3b1f>","#<Structs::Item:0x17e201e3>","#<Structs::Item:0x73f708bb>","#<Structs::Item:0x25f9b1d2>","#<Structs::Item:0x68a0e2b1>","#<Structs::Item:0x6fca0b5f>","#<Structs::Item:0x24b364cd>","#<Structs::Item:0x4c2c26a8>","#<Structs::Item:0x2376f0f6>","#<Structs::Item:0x1cd98734>","#<Structs::Item:0x23730d6e>","#<Structs::Item:0xe4766ce>","#<Structs::Item:0x1aa2c6b0>","#<Structs::Item:0x4a1212f7>","#<Structs::Item:0x71316ea6>","#<Structs::Item:0x44f51758>","#<Structs::Item:0x48eece30>","#<Structs::Item:0x1231f870>","#<Structs::Item:0x680ff0ce>","#<Structs::Item:0x4ac7540>","#<Structs::Item:0x3a8da4ab>","#<Structs::Item:0x276239f2>","#<Structs::Item:0x307c2450>","#<Structs::Item:0x571d516a>","#<Structs::Item:0x620fde>","#<Structs::Item:0x36791b89>","#<Structs::Item:0x67f6e7b2>","#<Structs::Item:0x5add6c27>","#<Structs::Item:0x4a51845d>","#<Structs::Item:0x340a6bcd>","#<Structs::Item:0x6491d189>","#<Structs::Item:0x559c3568>","#<Structs::Item:0x13a930ea>","#<Structs::Item:0x749a7551>","#<Structs::Item:0x1e6defd2>","#<Structs::Item:0x2a6eae02>","#<Structs::Item:0x709ae5c5>","#<Structs::Item:0x578d367a>","#<Structs::Item:0x26ef4026>","#<Structs::Item:0x79aef447>","#<Structs::Item:0x5e3d927a>","#<Structs::Item:0x60bd5121>","#<Structs::Item:0x3c8fc360>","#<Structs::Item:0x320d147a>","#<Structs::Item:0x91fe03>","#<Structs::Item:0xa2f9369>","#<Structs::Item:0x4879d58f>","#<Structs::Item:0x128db63e>","#<Structs::Item:0x1d63338a>","#<Structs::Item:0x6b214f94>","#<Structs::Item:0x6d723ad2>","#<Structs::Item:0x12315d04>","#<Structs::Item:0x164ad3ab>","#<Structs::Item:0x77766319>","#<Structs::Item:0xbae638f>","#<Structs::Item:0x136fc683>","#<Structs::Item:0x53f898ce>","#<Structs::Item:0x17525703>","#<Structs::Item:0x6f98ec7d>","#<Structs::Item:0x2ae74d3>","#<Structs::Item:0x1507b2a0>","#<Structs::Item:0x10e8154c>","#<Structs::Item:0x383be828>","#<Structs::Item:0x49c20b10>","#<Structs::Item:0x6178323a>","#<Structs::Item:0x316a192c>","#<Structs::Item:0x56f7dd81>","#<Structs::Item:0xfb4c6c4>","#<Structs::Item:0x2f7ddcea>","#<Structs::Item:0x4e3f1350>","#<Structs::Item:0x26ccd4c3>","#<Structs::Item:0xf67a438>","#<Structs::Item:0x4ebca3b2>"],"objective_func":1.0874763067776975e-18,"best_find_time":176.508,"elapsed_time":208.195,"problem_name":"LE_1"}
