{"solution":["#<Structs::Item:0x4b0490ca>","#<Structs::Item:0x635c4319>","#<Structs::Item:0x2b3dd76f>","#<Structs::Item:0x403cf47a>","#<Structs::Item:0x2f51be77>","#<Structs::Item:0x2e94640f>","#<Structs::Item:0x6b57481d>","#<Structs::Item:0x4c6ffe29>","#<Structs::Item:0x6eef43d5>","#<Structs::Item:0x63d6f61b>","#<Structs::Item:0x32104ddc>","#<Structs::Item:0x13d7301>","#<Structs::Item:0x15586918>","#<Structs::Item:0x41ea3386>","#<Structs::Item:0x71a4e8ca>","#<Structs::Item:0x1beb3884>","#<Structs::Item:0x4dad9248>","#<Structs::Item:0x5dcbfe78>","#<Structs::Item:0xb7fbfb3>","#<Structs::Item:0x49929940>","#<Structs::Item:0x680c7de8>","#<Structs::Item:0x6ab666af>","#<Structs::Item:0x1c42ce6d>","#<Structs::Item:0x41c70c3c>","#<Structs::Item:0x4aafcad1>","#<Structs::Item:0x13f55e35>","#<Structs::Item:0x19cedb80>","#<Structs::Item:0x60918269>","#<Structs::Item:0x545c35e8>","#<Structs::Item:0x6d61cda0>","#<Structs::Item:0x29c0957>","#<Structs::Item:0x6ef251a7>","#<Structs::Item:0x5bb4dae4>","#<Structs::Item:0x38db00ff>","#<Structs::Item:0x5a6f7002>","#<Structs::Item:0x26ec7d81>","#<Structs::Item:0x5bf2e042>","#<Structs::Item:0x3b4ecf3b>","#<Structs::Item:0x1a004730>","#<Structs::Item:0x5f452184>","#<Structs::Item:0x13793ade>","#<Structs::Item:0x5e03189d>","#<Structs::Item:0x46a2edaa>","#<Structs::Item:0x301dbdfb>","#<Structs::Item:0x6a68deec>","#<Structs::Item:0x2ce9f4cc>","#<Structs::Item:0x7df79346>","#<Structs::Item:0x20d80b66>","#<Structs::Item:0xceb3e2f>","#<Structs::Item:0x6f47e4ea>"],"objective_func":0.7813493793337991,"best_find_time":4.953,"elapsed_time":36.061,"problem_name":"MS_2"}
