{"solution":["#<Structs::Item:0x4937c320>","#<Structs::Item:0x4887b582>","#<Structs::Item:0x4eaa2443>","#<Structs::Item:0x7cfc4d63>","#<Structs::Item:0xb25bf1f>","#<Structs::Item:0x7e7b305c>","#<Structs::Item:0x616c8bec>","#<Structs::Item:0x7fe555f7>","#<Structs::Item:0x591ed053>","#<Structs::Item:0x7e40e2fc>","#<Structs::Item:0x7bf63533>","#<Structs::Item:0x2e698d57>","#<Structs::Item:0x1da5c81>","#<Structs::Item:0x78f40944>","#<Structs::Item:0x32e1f4c4>","#<Structs::Item:0x5080c4fa>","#<Structs::Item:0x36da43f>","#<Structs::Item:0x5b0b233f>","#<Structs::Item:0x6671bb4e>","#<Structs::Item:0x3080046e>","#<Structs::Item:0x5e22121d>","#<Structs::Item:0x5c32c03d>","#<Structs::Item:0x3772bb3e>","#<Structs::Item:0x7e16aca>","#<Structs::Item:0x499d22d1>","#<Structs::Item:0x3e420f7>","#<Structs::Item:0x21edd0fe>","#<Structs::Item:0x2d565933>","#<Structs::Item:0xdfd7de2>","#<Structs::Item:0x2fbc0732>","#<Structs::Item:0x6099581b>","#<Structs::Item:0x7f991afa>","#<Structs::Item:0x196d6a86>","#<Structs::Item:0x56a76b0e>","#<Structs::Item:0x7cd4a841>","#<Structs::Item:0x4b2d33eb>","#<Structs::Item:0x39e65952>","#<Structs::Item:0x54f4aa7b>","#<Structs::Item:0xd3b9604>","#<Structs::Item:0x2fab4e23>","#<Structs::Item:0x240cae4d>","#<Structs::Item:0x555a6fc5>","#<Structs::Item:0x40058dc>","#<Structs::Item:0x71afc429>","#<Structs::Item:0x30106297>","#<Structs::Item:0x36b20717>","#<Structs::Item:0x30f26fa5>","#<Structs::Item:0x3ff36b1e>","#<Structs::Item:0xc44a2ad>","#<Structs::Item:0x2ae8968d>"],"objective_func":0.9624315932328359,"best_find_time":0.406,"elapsed_time":31.437,"problem_name":"MB_14"}
