{"solution":["#<Structs::Item:0x7ad5c0fd>","#<Structs::Item:0x12b15a43>","#<Structs::Item:0x146edaa0>","#<Structs::Item:0x3a289585>","#<Structs::Item:0x6e2e6815>","#<Structs::Item:0x765554d1>","#<Structs::Item:0x140c2b61>","#<Structs::Item:0x6af610d8>","#<Structs::Item:0x7705b353>","#<Structs::Item:0x2baa82be>","#<Structs::Item:0x5e88e389>","#<Structs::Item:0x4225850>","#<Structs::Item:0x5e67ecac>","#<Structs::Item:0x21273aac>","#<Structs::Item:0x382a01aa>","#<Structs::Item:0x2edc2e27>","#<Structs::Item:0x4f3fb5dc>","#<Structs::Item:0x57d514cd>","#<Structs::Item:0x3f1a68cc>","#<Structs::Item:0x70f8c41e>","#<Structs::Item:0x42db1e88>","#<Structs::Item:0x3d571962>","#<Structs::Item:0x51675a0c>","#<Structs::Item:0x6789ac0a>","#<Structs::Item:0x7d3cc12d>","#<Structs::Item:0x78a55be1>","#<Structs::Item:0x13f9d9c3>","#<Structs::Item:0x39bade4a>","#<Structs::Item:0x221445f9>","#<Structs::Item:0x703c7809>","#<Structs::Item:0x2d56900c>","#<Structs::Item:0x42f14362>","#<Structs::Item:0x42cafd48>","#<Structs::Item:0x51253928>","#<Structs::Item:0x48ea15f0>","#<Structs::Item:0xc8a5dc>","#<Structs::Item:0x15fd2830>","#<Structs::Item:0x6d69afde>","#<Structs::Item:0x75346216>","#<Structs::Item:0x3017df29>","#<Structs::Item:0x4cd7cdb3>","#<Structs::Item:0x6c608ca8>","#<Structs::Item:0x3a1267e0>","#<Structs::Item:0x3472091c>","#<Structs::Item:0x463ae074>","#<Structs::Item:0x2ed731d7>","#<Structs::Item:0x7d37e8a>","#<Structs::Item:0x234dad85>","#<Structs::Item:0x3265c0d8>","#<Structs::Item:0x25ab06ca>"],"objective_func":0.8005870628480352,"best_find_time":3.516,"elapsed_time":34.812,"problem_name":"MB_11"}
