{"solution":["#<Structs::Item:0x4f888c52>","#<Structs::Item:0xd019d69>","#<Structs::Item:0x65059e89>","#<Structs::Item:0x3685b014>","#<Structs::Item:0x3de4408a>","#<Structs::Item:0x3c0f688a>","#<Structs::Item:0x75b75854>","#<Structs::Item:0x6ea953e6>","#<Structs::Item:0x71d6bea9>","#<Structs::Item:0x365ac321>","#<Structs::Item:0x79605846>","#<Structs::Item:0x5df212ef>","#<Structs::Item:0x1915cc0e>","#<Structs::Item:0x793657c6>","#<Structs::Item:0x26f82ce>","#<Structs::Item:0x4fc78d06>","#<Structs::Item:0x78855d4c>","#<Structs::Item:0x3346adfd>","#<Structs::Item:0x4d4130a9>","#<Structs::Item:0x3e1d3bba>"],"objective_func":0.7405304755056641,"best_find_time":0.031,"elapsed_time":31.108,"problem_name":"SS_14"}
