{"solution":["#<Structs::Item:0x5693175>","#<Structs::Item:0xde62baa>","#<Structs::Item:0xcb97d9a>","#<Structs::Item:0x2aebc8b1>","#<Structs::Item:0x6645b600>","#<Structs::Item:0x5ac27a19>","#<Structs::Item:0x1d508976>","#<Structs::Item:0x698a742d>","#<Structs::Item:0x22342aaa>","#<Structs::Item:0x6b6f9e47>","#<Structs::Item:0x726da165>","#<Structs::Item:0x48fc8819>","#<Structs::Item:0x4b9e9ad6>","#<Structs::Item:0x5c94a844>","#<Structs::Item:0x436d5c3a>","#<Structs::Item:0x6f7da80e>","#<Structs::Item:0x508ad71d>","#<Structs::Item:0x292583c0>","#<Structs::Item:0x808652>","#<Structs::Item:0x2bf6394>"],"objective_func":0.4200624049236668,"best_find_time":0.391,"elapsed_time":31.468,"problem_name":"SB_11"}
