{"solution":["#<Structs::Item:0x3bddc676>","#<Structs::Item:0x29a1505c>","#<Structs::Item:0x24db6ce>","#<Structs::Item:0x320a8ebf>","#<Structs::Item:0x67b100fe>","#<Structs::Item:0x44b18fe4>","#<Structs::Item:0x2ba5aa7a>","#<Structs::Item:0x4d3ca6c7>","#<Structs::Item:0x22e5f96e>","#<Structs::Item:0x6a638c79>","#<Structs::Item:0x6c931d35>","#<Structs::Item:0x44b194fe>","#<Structs::Item:0x49122b8f>","#<Structs::Item:0x3fe46690>","#<Structs::Item:0x4beabeec>","#<Structs::Item:0x3b4d50b>","#<Structs::Item:0x5b22d8a1>","#<Structs::Item:0x476ee5b3>","#<Structs::Item:0x59ed3e6c>","#<Structs::Item:0x7cd4a4d7>","#<Structs::Item:0x317e9c3c>","#<Structs::Item:0x18da4dd>","#<Structs::Item:0x31a3f4de>","#<Structs::Item:0x68880c21>","#<Structs::Item:0x2dd2e270>","#<Structs::Item:0x4195105b>","#<Structs::Item:0x6f3e19b3>","#<Structs::Item:0x47ffe971>","#<Structs::Item:0x7d04529c>","#<Structs::Item:0x14fa92af>","#<Structs::Item:0xb16e202>","#<Structs::Item:0x339a3670>","#<Structs::Item:0x6cd5122d>","#<Structs::Item:0x2c7a8af2>","#<Structs::Item:0x10c07b8d>","#<Structs::Item:0x720bf653>","#<Structs::Item:0x360bc645>","#<Structs::Item:0x4edef76c>","#<Structs::Item:0x5d51e129>","#<Structs::Item:0x70c53dbe>","#<Structs::Item:0x1894e40d>","#<Structs::Item:0x21c815e4>","#<Structs::Item:0x7342e05d>","#<Structs::Item:0x2a331b46>","#<Structs::Item:0x15383681>","#<Structs::Item:0x743e66f7>","#<Structs::Item:0x109a2025>","#<Structs::Item:0x2241f05b>","#<Structs::Item:0x761956ac>","#<Structs::Item:0x71978f46>","#<Structs::Item:0x304d0259>","#<Structs::Item:0x1d23ff23>","#<Structs::Item:0x2133661d>","#<Structs::Item:0x6c9320c2>","#<Structs::Item:0x3414a8c3>","#<Structs::Item:0x36cc9385>","#<Structs::Item:0xcf518cf>","#<Structs::Item:0x7915bca3>","#<Structs::Item:0x68d651f2>","#<Structs::Item:0x3ad4a7d6>","#<Structs::Item:0x1e43e323>","#<Structs::Item:0x4a67b4ec>","#<Structs::Item:0x10643593>","#<Structs::Item:0xf91da5e>","#<Structs::Item:0xeca6a74>","#<Structs::Item:0x79fd6f95>","#<Structs::Item:0x48840594>","#<Structs::Item:0x49c675f0>","#<Structs::Item:0x14823f76>","#<Structs::Item:0x6917bb4>","#<Structs::Item:0x6ed16657>","#<Structs::Item:0x1442f788>","#<Structs::Item:0x113e13f9>","#<Structs::Item:0x1c7f96b1>","#<Structs::Item:0x7979b8b7>","#<Structs::Item:0x7a04fea7>","#<Structs::Item:0x1bc49bc5>","#<Structs::Item:0x7b6e5c12>","#<Structs::Item:0x4f66ffc8>","#<Structs::Item:0x124ac145>","#<Structs::Item:0x2def7a7a>","#<Structs::Item:0x24e83d19>","#<Structs::Item:0x5c080ef3>","#<Structs::Item:0x188cbcde>","#<Structs::Item:0x4ee6291f>","#<Structs::Item:0x2b03d52f>","#<Structs::Item:0x37e0292a>","#<Structs::Item:0x4af70944>","#<Structs::Item:0x35267fd4>","#<Structs::Item:0x397ef2>","#<Structs::Item:0x36a6bea6>","#<Structs::Item:0x44e93c1f>","#<Structs::Item:0x42373389>","#<Structs::Item:0x9b21bd3>","#<Structs::Item:0xa62c7cd>","#<Structs::Item:0x7661b5a>","#<Structs::Item:0x7c36db44>","#<Structs::Item:0x65c33b92>","#<Structs::Item:0x7903d448>","#<Structs::Item:0x4e08acf9>"],"objective_func":0.6837946476946658,"elapsed_time":42.483,"best_find_time":22.546,"problem_name":"LS_7"}
