{"solution":["#<Structs::Item:0xa09303>","#<Structs::Item:0x1163a27>","#<Structs::Item:0x322ba549>","#<Structs::Item:0x502a4156>","#<Structs::Item:0x5416f8db>","#<Structs::Item:0x64e1377c>","#<Structs::Item:0xb0fd744>","#<Structs::Item:0x92d1782>","#<Structs::Item:0x6a1ef65c>","#<Structs::Item:0x72976b4>","#<Structs::Item:0x726934e2>","#<Structs::Item:0x1319bc2a>","#<Structs::Item:0xe280403>","#<Structs::Item:0x42f85fa4>","#<Structs::Item:0x798dad3d>","#<Structs::Item:0x27abb6ca>","#<Structs::Item:0x696db620>","#<Structs::Item:0x6968c1d6>","#<Structs::Item:0x7d986d83>","#<Structs::Item:0x77f991c>","#<Structs::Item:0x3a7e365>","#<Structs::Item:0x2ceee4b6>","#<Structs::Item:0x12a470dd>","#<Structs::Item:0x6968bcec>","#<Structs::Item:0x5568c66f>","#<Structs::Item:0xe784320>","#<Structs::Item:0x3f6bf8aa>","#<Structs::Item:0x13c8ac77>","#<Structs::Item:0x4bdf>","#<Structs::Item:0x4cad79bc>","#<Structs::Item:0x2c63762b>","#<Structs::Item:0x7a9eccc4>","#<Structs::Item:0x78422efb>","#<Structs::Item:0x5f05c8d6>","#<Structs::Item:0x68e02f33>","#<Structs::Item:0x64942607>","#<Structs::Item:0xd48e998>","#<Structs::Item:0x7cfac39f>","#<Structs::Item:0x158ae284>","#<Structs::Item:0x50eb4a2c>","#<Structs::Item:0x1a256d80>","#<Structs::Item:0x3069a360>","#<Structs::Item:0x7235f92b>","#<Structs::Item:0x7885776b>","#<Structs::Item:0x497d4c96>","#<Structs::Item:0x3472947a>","#<Structs::Item:0x69d3cf7e>","#<Structs::Item:0x3a3ed300>","#<Structs::Item:0x1984212d>","#<Structs::Item:0x39f5b723>"],"objective_func":1.9155486709776725e-14,"elapsed_time":17.203,"best_find_time":9.844,"problem_name":"ME_3"}
